pdf_parser_engine/__init__.py
pdf_parser_engine/pdf_parser_engine.py
tests/__init__.py
tests/test_parser.py
pdf_parser_engine-0.1.0.dist-info/METADATA
pdf_parser_engine-0.1.0.dist-info/WHEEL
pdf_parser_engine-0.1.0.dist-info/top_level.txt
pdf_parser_engine-0.1.0.dist-info/RECORD
