Metadata-Version: 2.1
Name: pdf_parser_engine
Version: 0.1.0
Summary: A text-in parser engine for pdf processing
Home-page: https://github.com/intsig/x2md_tools/python/text_in_parser_engine
Author: doughboii
License: UNKNOWN
Platform: UNKNOWN
Classifier: Programming Language :: Python :: 3
Classifier: License :: OSI Approved :: MIT License
Classifier: Operating System :: OS Independent
Requires-Python: >=3.6
